README.rst
setup.cfg
setup.py
bin/checkHotword.py
bin/trainHotword.py
hotword_detection/__init__.py
hotword_detection/dtw.py
hotword_detection/hwDetector.py
hotword_detection/mfcc.py
hotword_detection/wordRecorder.py
hotword_detection.egg-info/PKG-INFO
hotword_detection.egg-info/SOURCES.txt
hotword_detection.egg-info/dependency_links.txt
hotword_detection.egg-info/requires.txt
hotword_detection.egg-info/top_level.txt