Metadata-Version: 1.0
Name: hotword-detection
Version: 1.2
Summary: Python Hotword Detection
Home-page: https://github.com/sakethgsharma/HotWordDetection
Author: Prakhar Swarup, Saketh Sharma, Hitesh Tulsiani
Author-email: prkhrswrp@gmail.com
License: IITB
Platform: UNKNOWN
